arguably/__init__.py
arguably/__main__.py
arguably/_argparse_extensions.py
arguably/_commands.py
arguably/_context.py
arguably/_modifiers.py
arguably/_util.py
arguably/arg.py
arguably/py.typed
arguably-1.3.0.dist-info/LICENSE.txt
arguably-1.3.0.dist-info/METADATA
arguably-1.3.0.dist-info/WHEEL
arguably-1.3.0.dist-info/RECORD
