Metadata-Version: 2.1
Name: arguably
Version: 1.3.0
Summary: The best Python CLI library, arguably.
Home-page: https://treykeown.github.io/arguably/
Author: treykeown
Author-email: 2755914+treykeown@users.noreply.github.com
Requires-Python: >=3.9,<4.0
Classifier: Programming Language :: Python :: 3
Classifier: Programming Language :: Python :: 3.9
Classifier: Programming Language :: Python :: 3.10
Classifier: Programming Language :: Python :: 3.11
Classifier: Programming Language :: Python :: 3.12
Requires-Dist: docstring-parser (>=0.16,<0.17)
Project-URL: Repository, https://github.com/treykeown/arguably
